jsanctions
