Metadata-Version: 2.1
Name: django-jsanctions
Version: 3.6.14
Summary: Parses and imports EU combined sanction lists for Django projects
Home-page: https://github.com/kajala/django-jsanctions
Author: Jani Kajala
Author-email: kajala@gmail.com
License: MIT licence, see LICENCE.txt
License-File: LICENSE.txt
